mujoco_robot_environments/README.md
mujoco_robot_environments/__init__.py
mujoco_robot_environments/assets/mjcf/gala_apple/Apple.xml
mujoco_robot_environments/assets/mjcf/gala_apple/Apple1.obj
mujoco_robot_environments/assets/mjcf/gala_apple/Apple1.png
mujoco_robot_environments/assets/mjcf/gala_apple/Apple_edit.mtl
mujoco_robot_environments/assets/mjcf/gala_apple/Apple_edit.obj
mujoco_robot_environments/assets/mjcf/gala_apple/material.mtl
mujoco_robot_environments/assets/mjcf/tray/model.obj
mujoco_robot_environments/assets/mjcf/tray/model.xml
mujoco_robot_environments/assets/mjcf/tray/model_collision_0.obj
mujoco_robot_environments/assets/mjcf/tray/model_collision_1.obj
mujoco_robot_environments/assets/mjcf/tray/model_collision_10.obj
mujoco_robot_environments/assets/mjcf/tray/model_collision_11.obj
mujoco_robot_environments/assets/mjcf/tray/model_collision_12.obj
mujoco_robot_environments/assets/mjcf/tray/model_collision_13.obj
mujoco_robot_environments/assets/mjcf/tray/model_collision_14.obj
mujoco_robot_environments/assets/mjcf/tray/model_collision_15.obj
mujoco_robot_environments/assets/mjcf/tray/model_collision_16.obj
mujoco_robot_environments/assets/mjcf/tray/model_collision_17.obj
mujoco_robot_environments/assets/mjcf/tray/model_collision_18.obj
mujoco_robot_environments/assets/mjcf/tray/model_collision_19.obj
mujoco_robot_environments/assets/mjcf/tray/model_collision_2.obj
mujoco_robot_environments/assets/mjcf/tray/model_collision_20.obj
mujoco_robot_environments/assets/mjcf/tray/model_collision_21.obj
mujoco_robot_environments/assets/mjcf/tray/model_collision_22.obj
mujoco_robot_environments/assets/mjcf/tray/model_collision_23.obj
mujoco_robot_environments/assets/mjcf/tray/model_collision_24.obj
mujoco_robot_environments/assets/mjcf/tray/model_collision_25.obj
mujoco_robot_environments/assets/mjcf/tray/model_collision_26.obj
mujoco_robot_environments/assets/mjcf/tray/model_collision_27.obj
mujoco_robot_environments/assets/mjcf/tray/model_collision_28.obj
mujoco_robot_environments-0.1.0.dist-info/LICENSE
mujoco_robot_environments-0.1.0.dist-info/METADATA
mujoco_robot_environments-0.1.0.dist-info/WHEEL
mujoco_robot_environments-0.1.0.dist-info/RECORD
