Metadata-Version: 2.1
Name: mujoco_robot_environments
Version: 0.1.0
Summary: Simulation environments for basic manipulation tasks.
License: Apache-2.0
Author: Peter David Fagan
Author-email: peterdavidfagan@gmail.com
Requires-Python: ==3.10.6
Classifier: License :: OSI Approved :: Apache Software License
Classifier: Operating System :: POSIX :: Linux
Classifier: Programming Language :: Python :: 3
Requires-Dist: brax (>=0.10.4,<0.11.0)
Requires-Dist: dm-control (==1.0.16)
Requires-Dist: dm-reverb (==0.13.0) ; sys_platform == "linux"
Requires-Dist: envlogger[tfds] (>=1.2,<2.0) ; sys_platform == "linux"
Requires-Dist: evojax (>=0.2.16,<0.3.0)
Requires-Dist: evosax (>=0.1.6,<0.2.0)
Requires-Dist: huggingface-hub (>=0.23.0,<0.24.0)
Requires-Dist: hydra-core (>=1.3.2,<2.0.0)
Requires-Dist: inflect (>=7.0.0,<8.0.0)
Requires-Dist: ipywidgets (>=8.1.1,<9.0.0)
Requires-Dist: jupyterlab (>=4.0.9,<5.0.0)
Requires-Dist: lark (>=1.1.7,<2.0.0)
Requires-Dist: matplotlib (>=3.7.2,<4.0.0)
Requires-Dist: mujoco (>=3.1.1,<4.0.0)
Requires-Dist: mujoco_controllers (>=0.0.2,<0.0.3)
Requires-Dist: notebook (>=7.0.6,<8.0.0)
Requires-Dist: numpy (>=1.16.0,<2.0.0)
Requires-Dist: pillow (==10.0.0)
Requires-Dist: pytest (>=7.0.0,<8.0.0)
Requires-Dist: rlds (>=0.1.7,<0.2.0) ; sys_platform == "linux"
Requires-Dist: robot-descriptions (>=1.10.0,<2.0.0)
Requires-Dist: tensorflow-cpu (>=2.14.0,<3.0.0) ; sys_platform == "linux"
Requires-Dist: wandb (>=0.16.1,<0.17.0)
